ledwallcontroller/__init__.py
ledwallcontroller/api.py
ledwallcontroller/controller.py
ledwallcontroller/handler.py
ledwallcontroller-0.2.0.dist-info/METADATA
ledwallcontroller-0.2.0.dist-info/WHEEL
ledwallcontroller-0.2.0.dist-info/licenses/LICENSE
ledwallcontroller-0.2.0.dist-info/RECORD
