Metadata-Version: 2.4
Name: ledwallcontroller
Version: 0.2.0
Summary: An Interface to work with the Multivision and OnlyGlass Generic LED Controller via TCP
Author-email: Intermediate Engineering GmbH <info@im-en.com>
License-Expression: MIT
License-File: LICENSE
Classifier: Programming Language :: Python :: 3 :: Only
Classifier: Programming Language :: Python :: 3.11
Classifier: Programming Language :: Python :: 3.12
Classifier: Programming Language :: Python :: 3.13
Requires-Python: >=3.11
